{
  "timestamp": "2026-07-11T09:01:41.076037Z",
  "fear_greed": {
    "value": 26,
    "classification": "Fear"
  },
  "BTC": {
    "liquidity_score": 0,
    "direction": "NEUTRAL",
    "recommended_action": "NEUTRAL",
    "details": {
      "price": 64210,
      "change_24h": 0.07,
      "volume_24h": 20627737512.461147,
      "market_cap": 1287747510872.3926
    }
  },
  "ETH": {
    "liquidity_score": 0,
    "direction": "NEUTRAL",
    "recommended_action": "NEUTRAL",
    "details": {
      "price": 1799.91,
      "change_24h": 0.97,
      "volume_24h": 6787649807.830154,
      "market_cap": 217218345609.87622
    }
  },
  "version": "2.0"
}