{
  "timestamp": "2026-07-03T15:27:33.129960Z",
  "fear_greed": {
    "value": 21,
    "classification": "Extreme Fear"
  },
  "BTC": {
    "liquidity_score": 15,
    "direction": "NEUTRAL",
    "recommended_action": "NEUTRAL",
    "details": {
      "price": 61948,
      "change_24h": 0.37,
      "volume_24h": 28069292525.127476,
      "market_cap": 1242172412585.1414
    }
  },
  "ETH": {
    "liquidity_score": 15,
    "direction": "NEUTRAL",
    "recommended_action": "NEUTRAL",
    "details": {
      "price": 1732.68,
      "change_24h": 1.93,
      "volume_24h": 9008800052.563065,
      "market_cap": 209051975359.24597
    }
  },
  "version": "2.0"
}