{
  "timestamp": "2026-06-24T05:35:27.045727Z",
  "fear_greed": {
    "value": 17,
    "classification": "Extreme Fear"
  },
  "BTC": {
    "liquidity_score": 15,
    "direction": "NEUTRAL",
    "recommended_action": "NEUTRAL",
    "details": {
      "price": 62824,
      "change_24h": -0.92,
      "volume_24h": 31303953237.577217,
      "market_cap": 1258778830347.309
    }
  },
  "ETH": {
    "liquidity_score": 3,
    "direction": "NEUTRAL",
    "recommended_action": "NEUTRAL",
    "details": {
      "price": 1671.76,
      "change_24h": -2.29,
      "volume_24h": 9859870556.38199,
      "market_cap": 201610861440.08493
    }
  },
  "version": "2.0"
}