{
  "timestamp": "2026-07-08T03:52:46.475989Z",
  "fear_greed": {
    "value": 20,
    "classification": "Extreme Fear"
  },
  "BTC": {
    "liquidity_score": 15,
    "direction": "NEUTRAL",
    "recommended_action": "NEUTRAL",
    "details": {
      "price": 62814,
      "change_24h": -0.53,
      "volume_24h": 31949502280.279186,
      "market_cap": 1259727772740.6277
    }
  },
  "ETH": {
    "liquidity_score": 15,
    "direction": "NEUTRAL",
    "recommended_action": "NEUTRAL",
    "details": {
      "price": 1753.37,
      "change_24h": -0.95,
      "volume_24h": 9561464665.496836,
      "market_cap": 211687063823.45203
    }
  },
  "version": "2.0"
}