{
  "timestamp": "2026-07-17T17:07:21.015447Z",
  "fear_greed": {
    "value": 27,
    "classification": "Fear"
  },
  "BTC": {
    "liquidity_score": 0,
    "direction": "NEUTRAL",
    "recommended_action": "NEUTRAL",
    "details": {
      "price": 63642,
      "change_24h": -1.04,
      "volume_24h": 26237339505.391426,
      "market_cap": 1276298541516.9077
    }
  },
  "ETH": {
    "liquidity_score": 0,
    "direction": "NEUTRAL",
    "recommended_action": "NEUTRAL",
    "details": {
      "price": 1838.76,
      "change_24h": -1.9,
      "volume_24h": 9195744584.044382,
      "market_cap": 221908149081.05844
    }
  },
  "version": "2.0"
}