{
  "timestamp": "2026-07-05T20:25:44.144640Z",
  "fear_greed": {
    "value": 23,
    "classification": "Extreme Fear"
  },
  "BTC": {
    "liquidity_score": 15,
    "direction": "NEUTRAL",
    "recommended_action": "NEUTRAL",
    "details": {
      "price": 62708,
      "change_24h": -0.7,
      "volume_24h": 15619548406.326927,
      "market_cap": 1257485022095.6257
    }
  },
  "ETH": {
    "liquidity_score": 15,
    "direction": "NEUTRAL",
    "recommended_action": "NEUTRAL",
    "details": {
      "price": 1777.82,
      "change_24h": -0.34,
      "volume_24h": 10061612723.52149,
      "market_cap": 214565408708.09338
    }
  },
  "version": "2.0"
}