{
  "timestamp": "2026-07-24T01:39:09.883942Z",
  "fear_greed": {
    "value": 28,
    "classification": "Fear"
  },
  "BTC": {
    "liquidity_score": 0,
    "direction": "NEUTRAL",
    "recommended_action": "NEUTRAL",
    "details": {
      "price": 65076,
      "change_24h": -1.03,
      "volume_24h": 24797505935.940437,
      "market_cap": 1305459513194.911
    }
  },
  "ETH": {
    "liquidity_score": -12,
    "direction": "NEUTRAL",
    "recommended_action": "NEUTRAL",
    "details": {
      "price": 1875.47,
      "change_24h": -2.64,
      "volume_24h": 9494038252.179037,
      "market_cap": 226262774964.21793
    }
  },
  "version": "2.0"
}