{
  "timestamp": "2026-06-04T21:57:26.603770Z",
  "fear_greed": {
    "value": 12,
    "classification": "Extreme Fear"
  },
  "BTC": {
    "liquidity_score": 15,
    "direction": "NEUTRAL",
    "recommended_action": "NEUTRAL",
    "details": {
      "price": 63379,
      "change_24h": 0,
      "volume_24h": 0,
      "market_cap": 0
    }
  },
  "ETH": {
    "liquidity_score": 3,
    "direction": "NEUTRAL",
    "recommended_action": "NEUTRAL",
    "details": {
      "price": 1764.83,
      "change_24h": -4.34,
      "volume_24h": 27386768658.442577,
      "market_cap": 212809370217.98843
    }
  },
  "version": "2.0"
}