{
  "timestamp": "2026-07-19T02:36:36.604824Z",
  "fear_greed": {
    "value": 28,
    "classification": "Fear"
  },
  "BTC": {
    "liquidity_score": 0,
    "direction": "NEUTRAL",
    "recommended_action": "NEUTRAL",
    "details": {
      "price": 64811,
      "change_24h": 1.31,
      "volume_24h": 12339025329.910427,
      "market_cap": 1299985190447.9885
    }
  },
  "ETH": {
    "liquidity_score": 0,
    "direction": "NEUTRAL",
    "recommended_action": "NEUTRAL",
    "details": {
      "price": 1870.98,
      "change_24h": 1.53,
      "volume_24h": 5336833367.583316,
      "market_cap": 225795767088.16644
    }
  },
  "version": "2.0"
}