{
  "timestamp": "2026-06-25T12:04:30.094309Z",
  "fear_greed": {
    "value": 12,
    "classification": "Extreme Fear"
  },
  "BTC": {
    "liquidity_score": 3,
    "direction": "NEUTRAL",
    "recommended_action": "NEUTRAL",
    "details": {
      "price": 61169,
      "change_24h": -2.7,
      "volume_24h": 44530948976.529175,
      "market_cap": 1226267520133.584
    }
  },
  "ETH": {
    "liquidity_score": 3,
    "direction": "NEUTRAL",
    "recommended_action": "NEUTRAL",
    "details": {
      "price": 1629.69,
      "change_24h": -2.87,
      "volume_24h": 15580919548.632238,
      "market_cap": 196678807947.21548
    }
  },
  "version": "2.0"
}